httpenc.py
httpenc-0.0.1.dist-info/METADATA
httpenc-0.0.1.dist-info/WHEEL
httpenc-0.0.1.dist-info/top_level.txt
httpenc-0.0.1.dist-info/RECORD
